yysut
