Metadata-Version: 2.1
Name: yysut
Version: 0.0.2
Summary: YYSuperUtils
Home-page: UNKNOWN
Author: SuperYY
License: UNKNOWN
Platform: UNKNOWN
License-File: LICENSE
